mathplotlib/__init__.py
mathplotlib/parser.py
flowstats-0.1.0.dist-info/METADATA
flowstats-0.1.0.dist-info/WHEEL
flowstats-0.1.0.dist-info/top_level.txt
flowstats-0.1.0.dist-info/RECORD
