Metadata-Version: 2.4
Name: flowstats
Version: 0.1.0
Summary: mathplotlib
Home-page: https://github.com/yourusername/mathplotlib
Author: Ayush Chadha
Author-email: Ayush Chadha <elegantShock3307@gmail.com>
Project-URL: Homepage, https://github.com/elegantShock2258/mathplotlib
Keywords: math,simulator
Requires-Python: >=3.6
Dynamic: author
Dynamic: home-page
Dynamic: requires-python
